<annotation>
	<folder>new</folder>
	<filename>20.jpg</filename>
	<path>D:\Aras\Desktop\new\20.jpg</path>
	<source>
		<database>Unknown</database>
	</source>
	<size>
		<width>4160</width>
		<height>3120</height>
		<depth>3</depth>
	</size>
	<segmented>0</segmented>
	<object>
		<name>target</name>
		<pose>Unspecified</pose>
		<truncated>0</truncated>
		<difficult>0</difficult>
		<bndbox>
			<xmin>2002</xmin>
			<ymin>1469</ymin>
			<xmax>2216</xmax>
			<ymax>1671</ymax>
		</bndbox>
	</object>
	<object>
		<name>center</name>
		<pose>Unspecified</pose>
		<truncated>0</truncated>
		<difficult>0</difficult>
		<bndbox>
			<xmin>1558</xmin>
			<ymin>1104</ymin>
			<xmax>2605</xmax>
			<ymax>2107</ymax>
		</bndbox>
	</object>
	<object>
		<name>out</name>
		<pose>Unspecified</pose>
		<truncated>1</truncated>
		<difficult>1</difficult>
		<bndbox>
			<xmin>475</xmin>
			<ymin>436</ymin>
			<xmax>3297</xmax>
			<ymax>3120</ymax>
		</bndbox>
	</object>
	<object>
		<name>shot</name>
		<pose>Unspecified</pose>
		<truncated>0</truncated>
		<difficult>0</difficult>
		<bndbox>
			<xmin>1019</xmin>
			<ymin>1477</ymin>
			<xmax>1176</xmax>
			<ymax>1592</ymax>
		</bndbox>
	</object>
	<object>
		<name>shot</name>
		<pose>Unspecified</pose>
		<truncated>0</truncated>
		<difficult>0</difficult>
		<bndbox>
			<xmin>2180</xmin>
			<ymin>1301</ymin>
			<xmax>2320</xmax>
			<ymax>1412</ymax>
		</bndbox>
	</object>
	<object>
		<name>shot</name>
		<pose>Unspecified</pose>
		<truncated>0</truncated>
		<difficult>0</difficult>
		<bndbox>
			<xmin>2134</xmin>
			<ymin>2066</ymin>
			<xmax>2255</xmax>
			<ymax>2209</ymax>
		</bndbox>
	</object>
	<object>
		<name>shot</name>
		<pose>Unspecified</pose>
		<truncated>0</truncated>
		<difficult>0</difficult>
		<bndbox>
			<xmin>1734</xmin>
			<ymin>480</ymin>
			<xmax>1834</xmax>
			<ymax>563</ymax>
		</bndbox>
	</object>
</annotation>
